HISTORY.rst
LICENSE
MANIFEST.in
README.md
setup.cfg
setup.py
ci/refs.txt
docs/Makefile
docs/conf.py
docs/index.rst
docs/make.bat
docs/readme.rst
docs/usage.rst
docs/files/OAN.dat
docs/files/default.hjson
docs/files/results_summary_Ex_illus.txt
docs/files/results_summary_SNR.txt
docs/plots/Illustrative_example.png
docs/pyETC/Example_output.txt
docs/pyETC/authors.rst
docs/pyETC/contributing.rst
docs/pyETC/history.rst
docs/pyETC/installation.rst
pyETC/__init__.py
pyETC/camera.py
pyETC/cli.py
pyETC/constants.py
pyETC/display.py
pyETC/local_conditions.py
pyETC/optics.py
pyETC/photometry.py
pyETC/preliminary_computations.py
pyETC/pyETC.py
pyETC/set_object.py
pyETC/solver.py
pyETC/store_results.py
pyETC/utils.py
pyETC/write_results.py
pyETC.egg-info/PKG-INFO
pyETC.egg-info/SOURCES.txt
pyETC.egg-info/dependency_links.txt
pyETC.egg-info/entry_points.txt
pyETC.egg-info/not-zip-safe
pyETC.egg-info/requires.txt
pyETC.egg-info/top_level.txt
pyETC/config/CAGIRE_saturation.hjson
pyETC/config/Colibri_photoZ_mock.hjson
pyETC/config/GRB091020.hjson
pyETC/config/Make_one_image_etc.hjson
pyETC/config/Make_one_image_is.hjson
pyETC/config/example.hjson
pyETC/config/input_end2end.hjson
pyETC/config/tuto_grb_sim.hjson
pyETC/config/tuto_limiting_mag.hjson
pyETC/data/bohlin2006_Vega.dat
pyETC/data/LightCurves/LC_091020.txt
pyETC/data/LightCurves/LC_091020_VT_blue.txt
pyETC/data/calspec/10lac_stis_001.txt
pyETC/data/calspec/1732526_stisnic_001.txt
pyETC/data/calspec/1740346_stisnic_001.txt
pyETC/data/calspec/1743045_stisnic_001.txt
pyETC/data/calspec/1757132_stis_001.txt
pyETC/data/calspec/1802271_stisnic_001.txt
pyETC/data/calspec/1805292_stisnic_001.txt
pyETC/data/calspec/1808347_stis_001.txt
pyETC/data/calspec/1812095_stisnic_001.txt
pyETC/data/calspec/agk_81d266_stisnic_004.txt
pyETC/data/calspec/alpha_lyr_stis_006.txt
pyETC/data/calspec/bd02d3375_stis_001.txt
pyETC/data/calspec/bd21d0607_stis_001.txt
pyETC/data/calspec/bd26d2606_stis_001.txt
pyETC/data/calspec/bd29d2091_stis_001.txt
pyETC/data/calspec/bd54d1216_stis_001.txt
pyETC/data/calspec/bd60d1753_stis_001.txt
pyETC/data/calspec/bd_17d4708_stisnic_004.txt
pyETC/data/calspec/bd_25d4655_002.txt
pyETC/data/calspec/bd_28d4211_005.txt
