Metadata-Version: 2.1
Name: pyETC
Version: 0.1.1
Summary: Exposure Time Calculator for optical/NIR telescope
Home-page: https://github.com/dcorre/pyETC
Author: David Corre
Author-email: david.corre.fr@gmail.com
License: MIT license
Download-URL: https://github.com/dcorre/pyETC/archive/v0.1.1.tar.gz
Keywords: pyETC,ETC,Exposure Time Calculator,astronomy,telescope
Platform: UNKNOWN
Classifier: Development Status :: 4 - Beta
Classifier: Topic :: Scientific/Engineering :: Astronomy
Classifier: Intended Audience :: Science/Research
Classifier: License :: OSI Approved :: MIT License
Classifier: Natural Language :: English
Classifier: Programming Language :: Python :: 3
Classifier: Programming Language :: Python :: 3.6
Classifier: Programming Language :: Python :: 3.7
Classifier: Programming Language :: Python :: 3.8
